LICENSE
MANIFEST.in
README.md
requirements-style.txt
requirements-test.txt
requirements.txt
setup.cfg
setup.py
docker_python_dev.egg-info/PKG-INFO
docker_python_dev.egg-info/SOURCES.txt
docker_python_dev.egg-info/dependency_links.txt
docker_python_dev.egg-info/entry_points.txt
docker_python_dev.egg-info/namespace_packages.txt
docker_python_dev.egg-info/not-zip-safe
docker_python_dev.egg-info/requires.txt
docker_python_dev.egg-info/top_level.txt
docker_registry/__init__.py
docker_registry/../scaffold/driver/.editorconfig
docker_registry/../scaffold/driver/.gitignore
docker_registry/../scaffold/driver/.travis.yml
docker_registry/../scaffold/driver/AUTHORS
docker_registry/../scaffold/driver/LICENSE
docker_registry/../scaffold/driver/MANIFEST.in
docker_registry/../scaffold/driver/README.md
docker_registry/../scaffold/driver/docker-registry-project.sublime-project
docker_registry/../scaffold/driver/requirements.txt
docker_registry/../scaffold/driver/setup.cfg
docker_registry/../scaffold/driver/setup.py
docker_registry/../scaffold/driver/tox.ini
docker_registry/../scaffold/driver/docker_registry/__init__.py
docker_registry/../scaffold/driver/docker_registry/drivers/__init__.py
docker_registry/../scaffold/driver/docker_registry/drivers/{{driver.name}}.py
docker_registry/../scaffold/driver/tests/test.py
docker_registry/tools/__init__.py
docker_registry/tools/printer.py
docker_registry/tools/dpy/__init__.py
docker_registry/tools/driver/__init__.py