Metadata-Version: 1.1
Name: docker-python-dev
Version: 0.0.4
Summary: Docker python developers tools
Home-page: https://github.com/dmp42/docker-python-dev
Author: Mangled Deutz
Author-email: olivier@webitup.fr
License: 
